AUTHORS.rst
CONTRIBUTING.rst
HISTORY.rst
LICENSE
MANIFEST.in
README.rst
setup.cfg
setup.py
docs/Makefile
docs/authors.rst
docs/conf.py
docs/contributing.rst
docs/history.rst
docs/index.rst
docs/installation.rst
docs/make.bat
docs/readme.rst
docs/usage.rst
docs/_build/html/_static/ajax-loader.gif
docs/_build/html/_static/comment-bright.png
docs/_build/html/_static/comment-close.png
docs/_build/html/_static/comment.png
docs/_build/html/_static/down-pressed.png
docs/_build/html/_static/down.png
docs/_build/html/_static/file.png
docs/_build/html/_static/minus.png
docs/_build/html/_static/plus.png
docs/_build/html/_static/up-pressed.png
docs/_build/html/_static/up.png
shadow/__init__.py
shadow/cli.py
shadow/log.py
shadow/renderer.py
shadow/search.py
shadow/shadow.py
shadow_cli.egg-info/PKG-INFO
shadow_cli.egg-info/SOURCES.txt
shadow_cli.egg-info/dependency_links.txt
shadow_cli.egg-info/entry_points.txt
shadow_cli.egg-info/not-zip-safe
shadow_cli.egg-info/requires.txt
shadow_cli.egg-info/top_level.txt
tests/.test_shadow.py@neomake_18145_4.py
tests/.test_shadow.py@neomake_18145_43.py
tests/.test_shadow.py@neomake_18145_45.py
tests/.test_shadow.py@neomake_18145_59.py
tests/conftest.py
tests/test_shadow.py